MANIFEST.in
README.txt
setup.py
XStatic_Angular_Schema_Form.egg-info/PKG-INFO
XStatic_Angular_Schema_Form.egg-info/SOURCES.txt
XStatic_Angular_Schema_Form.egg-info/dependency_links.txt
XStatic_Angular_Schema_Form.egg-info/namespace_packages.txt
XStatic_Angular_Schema_Form.egg-info/not-zip-safe
XStatic_Angular_Schema_Form.egg-info/top_level.txt
xstatic/__init__.py
xstatic/pkg/__init__.py
xstatic/pkg/angular_schema_form/__init__.py
xstatic/pkg/angular_schema_form/data/WHERE_IS_BOOTSTRAP_DECORATOR.md
xstatic/pkg/angular_schema_form/data/bootstrap-decorator.js
xstatic/pkg/angular_schema_form/data/bootstrap-decorator.min.js
xstatic/pkg/angular_schema_form/data/schema-form.js
xstatic/pkg/angular_schema_form/data/schema-form.min.js