Metadata-Version: 1.0
Name: XStatic-Angular-Schema-Form
Version: 0.8.13.0
Summary: Angular-Schema-Form 0.8.13 (XStatic packaging standard)
Home-page: http://schemaform.io/
Author: Rob Cresswell
Author-email: robert.cresswell@outlook.com
License: MIT
Keywords: angular_schema_form xstatic
Platform: any
